LICENSE
MANIFEST.in
README.rst
setup.py
tox.ini
perftest/__init__.py
perftest/loader.py
perftest/suite.py
perftest.egg-info/PKG-INFO
perftest.egg-info/SOURCES.txt
perftest.egg-info/dependency_links.txt
perftest.egg-info/entry_points.txt
perftest.egg-info/requires.txt
perftest.egg-info/top_level.txt
perftest/.ropeproject/config.py